wx-stubs/ActivateEvent/__init__.py
wx-stubs/ActivateEvent/__init__.pyi
wx-stubs/ConfigBase/__init__.py
wx-stubs/ConfigBase/__init__.pyi
wx-stubs/DataObject/__init__.py
wx-stubs/DataObject/__init__.pyi
wx-stubs/DateTime/__init__.py
wx-stubs/DateTime/__init__.pyi
wx-stubs/FileType/__init__.py
wx-stubs/FileType/__init__.pyi
wx-stubs/HelpEvent/__init__.py
wx-stubs/HelpEvent/__init__.pyi
wx-stubs/Image/__init__.py
wx-stubs/Image/__init__.pyi
wx-stubs/StandardPaths/__init__.py
wx-stubs/StandardPaths/__init__.pyi
wx-stubs/StaticBitmap/__init__.py
wx-stubs/StaticBitmap/__init__.pyi
wx-stubs/StockPreferencesPage/__init__.py
wx-stubs/StockPreferencesPage/__init__.pyi
wx-stubs/TopLevelWindow/__init__.py
wx-stubs/TopLevelWindow/__init__.pyi
wx-stubs/Window/__init__.py
wx-stubs/Window/__init__.pyi
wx-stubs/__init__.py
wx-stubs/__init__.pyi
wx-stubs/adv/__init__.py
wx-stubs/adv/__init__.pyi
wx-stubs/aui/__init__.py
wx-stubs/aui/__init__.pyi
wx-stubs/dataview/__init__.py
wx-stubs/dataview/__init__.pyi
wx-stubs/glcanvas/__init__.py
wx-stubs/glcanvas/__init__.pyi
wx-stubs/grid/Grid/__init__.py
wx-stubs/grid/Grid/__init__.pyi
wx-stubs/grid/GridActivationSource/__init__.py
wx-stubs/grid/GridActivationSource/__init__.pyi
wx-stubs/grid/GridBlocks/__init__.py
wx-stubs/grid/GridBlocks/__init__.pyi
wx-stubs/grid/__init__.py
wx-stubs/grid/__init__.pyi
wx-stubs/html/__init__.py
wx-stubs/html/__init__.pyi
wx-stubs/html2/__init__.py
wx-stubs/html2/__init__.pyi
wx-stubs/lib/__init__.py
wx-stubs/lib/agw/__init__.py
wx-stubs/lib/agw/__init__.pyi
wx-stubs/lib/agw/aui/__init__.py
wx-stubs/lib/agw/aui/auibar/__init__.py
wx-stubs/lib/agw/aui/auibar/__init__.pyi
wx-stubs/lib/agw/aui/auibook/__init__.py
wx-stubs/lib/agw/aui/auibook/__init__.pyi
wx-stubs/lib/agw/aui/framemanager/__init__.py
wx-stubs/lib/agw/aui/framemanager/__init__.pyi
wx-stubs/lib/agw/aui/tabart/__init__.py
wx-stubs/lib/agw/aui/tabart/__init__.pyi
wx-stubs/lib/agw/aui/tabmdi/__init__.py
wx-stubs/lib/agw/aui/tabmdi/__init__.pyi
types_wxpython-0.9.7.dist-info/LICENSE
types_wxpython-0.9.7.dist-info/METADATA
types_wxpython-0.9.7.dist-info/WHEEL
types_wxpython-0.9.7.dist-info/RECORD
