Metadata-Version: 2.1
Name: types-wxpython
Version: 0.9.7
Summary: Typing stubs for wxPython
Home-page: https://github.com/AlexionSoftware/types-wxpython
License: MIT
Keywords: wxPython,typing,stubs,wx
Author: Alexion Software
Author-email: info@alexion.nl
Requires-Python: >=3.8.1,<4.0.0
Classifier: License :: OSI Approved :: MIT License
Classifier: Programming Language :: Python :: 3
Classifier: Programming Language :: Python :: 3.9
Classifier: Programming Language :: Python :: 3.10
Classifier: Programming Language :: Python :: 3.11
Classifier: Programming Language :: Python :: 3.12
Project-URL: Repository, https://github.com/AlexionSoftware/types-wxpython
